LICENSE
MANIFEST.in
README.md
setup.cfg
setup.py
gdpstorage/__init__.py
gdpstorage/apps.py
gdpstorage/gd_service.py
gdpstorage/storage.py
gdpstorage/urls.py
gdpstorage/views.py
gdpstorage.egg-info/PKG-INFO
gdpstorage.egg-info/SOURCES.txt
gdpstorage.egg-info/dependency_links.txt
gdpstorage.egg-info/requires.txt
gdpstorage.egg-info/top_level.txt
gdpstorage/migrations/__init__.py
gdpstorage/models/__init__.py
gdpstorage/models/softdelete.py
gdpstorage/models/timestamp.py