Metadata-Version: 2.1
Name: gdpstorage
Version: 0.1.7
Summary: Storage Engine for Django Project based on Google Drive Personal Drive
Home-page: UNKNOWN
Author: JADLI AISSAM
Author-email: jadliaissam@gmail.com
License: MIT
Project-URL: Project Homepage, https://github.com/jadliaissam/django-gdpstorage
Platform: UNKNOWN
Classifier: Environment :: Web Environment
Classifier: Framework :: Django
Classifier: Framework :: Django :: 3.2
Classifier: Intended Audience :: Developers
Classifier: License :: OSI Approved :: BSD License
Classifier: Operating System :: OS Independent
Classifier: Programming Language :: Python
Classifier: Programming Language :: Python :: 3
Classifier: Programming Language :: Python :: 3 :: Only
Classifier: Programming Language :: Python :: 3.7
Classifier: Programming Language :: Python :: 3.8
Classifier: Topic :: Internet :: WWW/HTTP
Classifier: Topic :: Internet :: WWW/HTTP :: Dynamic Content
